dumpyara/__init__.py
dumpyara/__main__.py
dumpyara/dumpyara.py
dumpyara/lib/liberofs/__init__.py
dumpyara/lib/libkdz/__init__.py
dumpyara/lib/libkdz/dz.py
dumpyara/lib/libkdz/gpt.py
dumpyara/lib/libkdz/kdz.py
dumpyara/lib/libkdz/undz.py
dumpyara/lib/libkdz/unkdz.py
dumpyara/lib/libpayload/LICENSE
dumpyara/lib/libpayload/__init__.py
dumpyara/lib/libpayload/update_metadata_pb2.py
dumpyara/lib/libsdat2img/__init__.py
dumpyara/lib/libsevenzip/__init__.py
dumpyara/main.py
dumpyara/steps/__init__.py
dumpyara/steps/extract_archive.py
dumpyara/steps/extract_images.py
dumpyara/steps/prepare_images.py
dumpyara/utils/bootimg.py
dumpyara/utils/files.py
dumpyara/utils/multipartitions.py
dumpyara/utils/partitions.py
dumpyara/utils/raw_image.py
dumpyara/utils/shutil.py
dumpyara/utils/sparsed_images.py
dumpyara-1.0.10.dist-info/METADATA
dumpyara-1.0.10.dist-info/WHEEL
dumpyara-1.0.10.dist-info/entry_points.txt
dumpyara-1.0.10.dist-info/RECORD
