Metadata-Version: 2.3
Name: dumpyara
Version: 1.0.10
Summary: Android firmware extractor
License: GPL-3.0
Author: Sebastiano Barezzi
Author-email: seba@sebaubuntu.dev
Requires-Python: >=3.8,<4.0
Classifier: License :: OSI Approved :: GNU General Public License v3 (GPLv3)
Classifier: Programming Language :: Python :: 3
Classifier: Programming Language :: Python :: 3.8
Classifier: Programming Language :: Python :: 3.9
Classifier: Programming Language :: Python :: 3.10
Classifier: Programming Language :: Python :: 3.11
Classifier: Programming Language :: Python :: 3.12
Classifier: Programming Language :: Python :: 3.13
Requires-Dist: Brotli (>=1.0.9,<2.0.0)
Requires-Dist: liblp (>=1.0.2,<2.0.0)
Requires-Dist: lz4 (>=4.3.3,<5.0.0)
Requires-Dist: protobuf (>=4.22.1,<6.0.0)
Requires-Dist: py7zr (>=0.21,<0.23)
Requires-Dist: sebaubuntu-libs (>=1.4.5,<2.0.0)
Requires-Dist: zstandard (>=0.23.0,<0.24.0)
Project-URL: Repository, https://github.com/sebaubuntu-python/dumpyara
